edgardsrs/__init__.py
edgardsrs/module.py
edgardsrs-0.1.1.dist-info/LICENSE
edgardsrs-0.1.1.dist-info/METADATA
edgardsrs-0.1.1.dist-info/WHEEL
edgardsrs-0.1.1.dist-info/top_level.txt
edgardsrs-0.1.1.dist-info/RECORD
