Metadata-Version: 2.1
Name: edgardsrs
Version: 0.1.1
Summary: A tool for cleaning SEC EDGAR HTML files
Home-page: https://github.com/pratikrelekar/EdgarDSRS
Author: Pratik Relekar, Xinyao Qian
Author-email: relekar2@illinois.edu, xinyaoq2@illinois.edu
Classifier: Programming Language :: Python :: 3
Classifier: License :: OSI Approved :: MIT License
Classifier: Operating System :: OS Independent
Requires-Python: >=3.6
License-File: LICENSE
Requires-Dist: beautifulsoup4>=4.9.3
Requires-Dist: lxml>=4.9.0
